encor-1.1.5.dist-info/RECORD
encor-1.1.5.dist-info/WHEEL
encor-1.1.5.dist-info/top_level.txt
encor-1.1.5.dist-info/METADATA
encor-1.1.5.dist-info/licenses/LICENSE.md
acor/_acor.cpython-312-darwin.so
acor/acor.c
acor/__init__.py
acor/_acor.c
acor/acor.py
acor/acor.h
