Metadata-Version: 2.4
Name: encor
Version: 1.1.5
Summary: Estimate the autocorrelation time of a time series quickly.
Author-email: Daniel Foreman-Mackey and Jonathan Goodman <danfm@nyu.edu>
Maintainer-email: David Wright <david.wright@nanograv.org>
Project-URL: Homepage, http://github.com/davecwright3/acor
Classifier: Development Status :: 3 - Alpha
Classifier: Intended Audience :: Science/Research
Classifier: License :: OSI Approved :: MIT License
Classifier: Operating System :: OS Independent
Classifier: Programming Language :: Python
License-File: LICENSE.md
Requires-Dist: numpy
Dynamic: license-file
